{"cameraMode":{"drawMode":0,"name":"Shaded","section":"Shading Mode"},"sceneLighting":true,"audioPlay":false,"sceneViewState":{"m_AlwaysRefresh":false,"showFog":true,"showSkybox":true,"showFlares":true,"showImageEffects":true,"showParticleSystems":true,"showVisualEffectGraphs":true,"m_FxEnabled":true},"in2DMode":false,"pivot":{"x":88.7899169921875,"y":12.252376556396485,"z":-19.27503204345703},"rotation":{"x":0.12566475570201875,"y":-0.006843020208179951,"z":0.0008680492173880339,"w":0.9920551776885986},"size":4.780561447143555,"orthographic":false}